openwebif/__init__.py
openwebif/api.py
openwebif/constants.py
openwebif/enums.py
openwebif/error.py
openwebif/py.typed
openwebifpy-4.3.0.dist-info/METADATA
openwebifpy-4.3.0.dist-info/WHEEL
openwebifpy-4.3.0.dist-info/licenses/LICENSE
openwebifpy-4.3.0.dist-info/RECORD
