Metadata-Version: 2.3
Name: openwebifpy
Version: 4.3.0
Summary: Provides a python interface to interact with a device running OpenWebIf
Project-URL: Homepage, https://github.com/autinerd/openwebifpy
Author-email: Finbarr Brady <fbradyirl@github.io>, Sidney Kuyateh <autinerd@kuyateh.eu>
Maintainer-email: Sidney Kuyateh <autinerd@kuyateh.eu>
License: MIT License
Keywords: openwebif
Classifier: Development Status :: 2 - Pre-Alpha
Classifier: Intended Audience :: Developers
Classifier: License :: OSI Approved :: MIT License
Classifier: Natural Language :: English
Classifier: Programming Language :: Python :: 3 :: Only
Requires-Dist: aiohttp
Requires-Dist: yarl
